gitco/__init__.py
gitco/cli.py
gitco/gitco.py
gitco/inputs.py
gitco/utils.py
gitco-0.0.5.dist-info/METADATA
gitco-0.0.5.dist-info/WHEEL
gitco-0.0.5.dist-info/entry_points.txt
gitco-0.0.5.dist-info/licenses/LICENSE
gitco-0.0.5.dist-info/RECORD
