Metadata-Version: 2.3
Name: gitco
Version: 0.0.5
Summary: A simple command to generate git commit messages from the current diff file
Project-URL: Homepage, https://github.com/Valkea/gitco
Project-URL: Issues, https://github.com/Valkea/gitco/issues
Author-email: Emmanuel Letremble <gitco@shedge.com>
License-File: LICENSE
Classifier: License :: OSI Approved :: MIT License
Classifier: Operating System :: OS Independent
Classifier: Programming Language :: Python :: 3
Requires-Python: >=3.10
Requires-Dist: instructor
Requires-Dist: openai
Requires-Dist: prompt-toolkit
Requires-Dist: python-dotenv
Requires-Dist: requests
